cliprophesy/README.md
cliprophesy/__init__.py
cliprophesy/common.py
cliprophesy/install.sh
cliprophesy/main.py
cliprophesy/inputs/ShellReader.py
cliprophesy/inputs/__init__.py
cliprophesy/inputs/formatting.py
cliprophesy/llms/__init__.py
cliprophesy/llms/anthropic_backend.py
cliprophesy/llms/base.py
cliprophesy/llms/clibuddy.py
cliprophesy/llms/local_backend.py
cliprophesy/llms/openai_backend.py
cliprophesy/llms/prompts.py
cliprophesy-0.0.8.dist-info/METADATA
cliprophesy-0.0.8.dist-info/WHEEL
cliprophesy-0.0.8.dist-info/entry_points.txt
cliprophesy-0.0.8.dist-info/licenses/LICENSE
cliprophesy-0.0.8.dist-info/RECORD
