Metadata-Version: 2.4
Name: cliprophesy
Version: 0.0.8
Summary: Get command line suggestions
Project-URL: Homepage, https://github.com/cliseer/cliprophesy
Project-URL: Issues, https://github.com/cliseer/cliprophesy/issues
Author-email: Yaron Greif <ygreif@gmail.com>
License-Expression: MIT
License-File: LICENSE
Classifier: Operating System :: OS Independent
Classifier: Programming Language :: Python :: 3
Requires-Python: >=3.6
